easymdm/__init__.py
easymdm/a_start_point.py
easymdm/b_data_source.py
easymdm/c_blocking.py
easymdm/cli.py
easymdm/d_similarity.md
easymdm/d_similarity.py
easymdm/e_priority_survivor.md
easymdm/e_priority_survivor.py
easymdm/f_csv_to_duckdb.py
easymdm/f_duckdb_logic copy.py
easymdm/f_duckdb_logic.py
easymdm-0.1.2.dist-info/METADATA
easymdm-0.1.2.dist-info/WHEEL
easymdm-0.1.2.dist-info/entry_points.txt
easymdm-0.1.2.dist-info/licenses/LICENSE
easymdm-0.1.2.dist-info/RECORD
