Metadata-Version: 2.4
Name: easymdm
Version: 0.1.2
Summary: easymdm is an open source mdm system, usefull for user data consolidation.
Author-email: ankit K <ankit48365@gmail.com>
License-File: LICENSE
Requires-Python: >=3.13
Requires-Dist: duckdb>=1.3.2
Requires-Dist: fuzzywuzzy>=0.18.0
Requires-Dist: networkx>=3.5
Requires-Dist: pandas>=2.3.1
Requires-Dist: pyaml>=25.7.0
Requires-Dist: python-levenshtein>=0.27.1
Requires-Dist: recordlinkage>=0.16
